whatcd/__init__.py
whatcd/whatcd.py
whatcd_cau-0.1.0a1.dist-info/DESCRIPTION.rst
whatcd_cau-0.1.0a1.dist-info/METADATA
whatcd_cau-0.1.0a1.dist-info/RECORD
whatcd_cau-0.1.0a1.dist-info/WHEEL
whatcd_cau-0.1.0a1.dist-info/metadata.json
whatcd_cau-0.1.0a1.dist-info/top_level.txt
