Metadata-Version: 2.0
Name: whatcd-cau
Version: 0.1.0a1
Summary: Create and upload torrents to What.cd
Home-page: https://github.com/creemerica/whatcd-cau.git
Author: Spencer Cree
Author-email: UNKNOWN
License: MIT
Keywords: whatcd,upload,torrent,mktorrent
Platform: UNKNOWN
Classifier: Development Status :: 3 - Alpha
Classifier: Intended Audience :: Developers
Classifier: Topic :: Software Development :: Build Tools
Classifier: License :: OSI Approved :: MIT License
Classifier: Programming Language :: Python :: 2.7
Classifier: Programming Language :: Python :: 3
Classifier: Programming Language :: Python :: 3.2
Classifier: Programming Language :: Python :: 3.3
Classifier: Programming Language :: Python :: 3.4
Requires-Dist: requests (==2.7.0)
